micropython_bmi160/__init__.py
micropython_bmi160/bmi160.py
micropython_bmi160/i2c_helpers.py
micropython_bmi160-0.1.2.dist-info/LICENSE
micropython_bmi160-0.1.2.dist-info/METADATA
micropython_bmi160-0.1.2.dist-info/WHEEL
micropython_bmi160-0.1.2.dist-info/top_level.txt
micropython_bmi160-0.1.2.dist-info/RECORD
