Metadata-Version: 2.1
Name: micropython-bmi160
Version: 0.1.2
Summary: MicroPython Driver for the Bosch BMI160 Acc/Gyro Sensor
Author-email: JDM <xxyx@mailmeto.mozmail.com>
License: MIT
Project-URL: Homepage, https://github.com/jposada202020/MicroPython_BMI160
Keywords: sensor,micropython,bmi160,gyro,acceleration,accelerometer,temperature,vector,gravity,micropython,rotation
Classifier: Intended Audience :: Developers
Classifier: Topic :: Software Development :: Libraries
Classifier: Topic :: Software Development :: Embedded Systems
Classifier: Topic :: System :: Hardware
Classifier: License :: OSI Approved :: MIT License
Classifier: Programming Language :: Python :: Implementation :: MicroPython
License-File: LICENSE
